src/output_register.v
module output_register(clk, Eout, inputData, outputData);

    // clk is main input clock
    // Eout is input enable signal for output register
    // inputData is input data for output register
    // outputData is output data for output register

    input clk;
    input Eout;
    input [7:0] inputData;
    output reg[7:0] outputData;

    always@(posedge clk)
    begin
        if(Eout)
            outputData <= inputData;
        else
            outputData <= outputData;
    end
endmodule

src/alu.v
module alu(inputA, inputB, aluOutput, subtract);

    // inputA is data from Accumulator
    // inputB is data fro b register
    // subtract is flag signal to enable subtraction instead of addition
    // aluOutput is output of ALU

    input [7:0] inputA, inputB;
    input subtract;
    output reg[7:0] aluOutput;

    always@(inputA,inputB,subtract)
    begin
        if(subtract)
            aluOutput = inputA - inputB;
        else
            aluOutput = inputA + inputB;
    end
endmodule

src/b_register.v
module b_register(clk, Eb, inputData, outputData);

    // clk is main input clock
    // Eb is input enable signal for b register
    // inputData is input data for b register
    // outputData is output data for b register

    input clk;
    input Eb;
    input [7:0] inputData;
    output reg[7:0] outputData;

    always@(posedge clk)
    begin
        if(Eb)
            outputData <= inputData;
        else
            outputData <= outputData;
    end
endmodule

src/accumulator.v
module accumulator(clk, Eacc, LaccM, LaccA, inputDataFromMemory, inputDataFromALU, outputDataAcc);

    // clk is main input clock
    // Eacc is input enable signal for accumulator
    // LaccM is input enable to load data from ROM
    // LaccA is input enable to load data from ALU
    // inputDataFromMemory is data to be loaded from ROM
    // inputDataFromALU is data to be loaded from ALU
    // outputDataAcc is output data of Accululator

    input clk;
    input Eacc;
    input LaccM;
    input LaccA;
    input [7:0] inputDataFromMemory;
    input [7:0] inputDataFromALU;
    output reg[7:0] outputDataAcc;

    always@(posedge clk)
    begin
        if(Eacc)
            if(LaccM)
                outputDataAcc <= inputDataFromMemory;
            else if(LaccA)
                outputDataAcc <= inputDataFromALU;
            else
                outputDataAcc <= outputDataAcc;
        else
            outputDataAcc <= outputDataAcc;
    end
endmodule

src/instruction_register.v
module instruction_register(clk, Eir, inputInstruction, outputInstruction);

    // clk is main input clock
    // Eir is input enable signal for instruction register
    // inputInstruction is input instruction from memory to the instruction register (IR)
    // outputInstruction is stored instruction register

    input clk;
    input Eir;
    input [7:0] inputInstruction;
    output reg[7:0] outputInstruction;

    always@(posedge clk)
    begin
        if(Eir)
            outputInstruction <= inputInstruction;
        else
            outputInstruction <= outputInstruction;
    end
endmodule

src/memory_16x8_rom.v
module memory_16x8_rom(clk, readEnable, readAddress, dataOut);

    parameter ROM_WIDTH = 8;
    parameter ROM_DEPTH = 16;
    parameter ADDRESS_SIZE = 4;

    input clk;
    input readEnable;
    input [ADDRESS_SIZE-1:0] readAddress;
    output reg [ROM_WIDTH-1:0] dataOut;

    /* Following is ISA opcodes for SAP-1
        Mnemonics   | Opcode
        ------------------
        LDA         | 0000
        ADD         | 0001
        SUB         | 0010
        OUT         | 1110
        HLT         | 1111

        Based on above mapping, loading memory with following code.
        LDA 0x9 = 0000 1001
        ADD 0xA = 0001 1010
        ADD 0xB = 0001 1011
        SUB 0xC = 0010 1100
        OUT     = 1110 XXXX
        HLT     = 1111 XXXX

    */


    reg [ROM_WIDTH-1:0] mem [ROM_DEPTH-1:0];
    
    //Initializing the memory , not sure if this is correct and synthesizable, will see
    //integer i;
    //initial begin
    //    for(i=0; i<ROM_DEPTH; i=i+1)
    //        mem[i] = i+3;
    //end
    //Initialized the memory as per above code 
        initial begin
        mem[0]  = 8'b00001001;
        mem[1]  = 8'b11101111;
        mem[2]  = 8'b00011010;
        mem[3]  = 8'b11101111;
        mem[4]  = 8'b00011011;
        mem[5]  = 8'b11101111;
        mem[6]  = 8'b00101100;
        mem[7]  = 8'b11101111;
        mem[8]  = 8'b11101111;
        mem[9]  = 8'b00000001;
        mem[10] = 8'b00000010;
        mem[11] = 8'b00000011;
        mem[12] = 8'b00000100;
        mem[13] = 8'b11111111;
        mem[14] = 8'b11111111;
        mem[15] = 8'b11111111;
    end
    

    always@(posedge clk)
    begin
        if (readEnable)
            dataOut <= mem[readAddress];
        else
            dataOut <= dataOut;
    end

endmodule

src/mar.v
module mar(clk, Emar, LmPC, LmIRa, addressFromPC, addressFromIR, outputAddress);

    input clk;
    input Emar;
    input LmPC;
    input LmIRa;
    input [3:0] addressFromPC;
    input [3:0] addressFromIR;
    output reg[3:0] outputAddress;

    // clk is main input clock
    // Emar is synchronous enable signal for MAR
    // LmPC stands for load MAR with address from PC, this active high signal enables loading of MAR with PC address
    // LmIRa stans for load MAR with address from IR's lower nibble 
    // rest of the names are self explainatory

    always@(posedge clk)
    begin
        if(Emar)
            if(LmPC)
                outputAddress <= addressFromPC;
            else if(LmIRa)
                outputAddress <= addressFromIR;
            else
                outputAddress <= outputAddress;
        else
            outputAddress <= outputAddress;
    end

endmodule

src/program_counter.v
module program_counter(input clk, rst, Epc, output reg[3:0] pc_address);

    //making asynch reset
    always@(posedge clk or posedge rst)
    begin
      if(rst)
        	pc_address <= 4'd0;
      else
	      if(Epc)
          	pc_address <= pc_address + 1'b1;
    end
endmodule

src/control_unit.v
module control_unit(clk, rst, inputInstruction, Epc, RstPc, Emar, LmPC, LmIRa, readEnableROM, Eir, Eacc, LaccM, LaccA, Eb, subtract,Eo);

    input clk, rst;
    input [7:0] inputInstruction;
    output Epc, RstPc, Emar, LmPC, LmIRa, readEnableROM, Eir, Eacc, LaccM, LaccA, Eb, subtract,Eo;

    parameter IDLE = 8'b00000001;
    parameter T1   = 8'b00000010;
    parameter T2   = 8'b00000100;
    parameter T3   = 8'b00001000;
    parameter T4   = 8'b00010000;
    parameter T5   = 8'b00100000;
    parameter T6   = 8'b01000000;
    parameter T7   = 8'b10000000;

    reg [7:0] present, next;

    always@(negedge clk)  // present state logic
    begin
        if(rst)
            present <= IDLE;
        else
            present <= next;
    end

    always@(present,inputInstruction) // next state logic
    begin
        next = IDLE; // Default state
        case(present)
            IDLE: begin next = T1; end
            T1: begin next = T2; end
            T2: begin next = T3; end
            T3: begin next = T4; end
            T4: begin next = T5; end
            T5: begin next = T6; end
            T6: begin next = T7; end
            T7: begin next = T1; end
        endcase
    end

    assign RstPc            = (present == IDLE) ? 1:0;
    assign Emar             = (present == T1 || (present == T4 && (inputInstruction[7:4] == 4'b0000 || inputInstruction[7:4] == 4'b0001 || inputInstruction[7:4] == 4'b0010))) ? 1:0;
    assign LmPC             = (present == T1) ? 1:0;
    assign Epc              = (present == T2) ? 1:0;
    assign readEnableROM    = (present == T2 || (present == T5 && (inputInstruction[7:4] == 4'b0000 || inputInstruction[7:4] == 4'b0001 || inputInstruction[7:4] == 4'b0010))) ? 1:0;
    assign Eir              = (present == T3) ? 1:0;
    assign LmIRa            = (present == T4 && (inputInstruction[7:4] == 4'b0000 || inputInstruction[7:4] == 4'b0001 || inputInstruction[7:4] == 4'b0010)) ? 1:0;
    assign Eacc             = ((present == T6 && inputInstruction[7:4] == 4'b0000) || (present == T7 && (inputInstruction[7:4] == 4'b0001 || inputInstruction[7:4] == 4'b0010))) ? 1:0;
    assign LaccM            = (present == T6 && inputInstruction[7:4] == 4'b0000) ? 1:0;
    assign LaccA            = (present == T7 && (inputInstruction[7:4] == 4'b0001 || inputInstruction[7:4] == 4'b0010)) ? 1:0;
    assign Eb               = (present == T6 && (inputInstruction[7:4] == 4'b0001 || inputInstruction[7:4] == 4'b0010)) ? 1:0;
    assign subtract         = ((present == T6 || present == T7 ) && inputInstruction[7:4] == 4'b0010) ? 1:0;
    assign Eo               = (present == T4 && inputInstruction[7:4] == 4'b1110);

endmodule

src/tt_um_jayraj4021_SAP1_cpu.v
`include "./program_counter.v"
`include "./control_unit.v"
`include "./mar.v"
`include "./memory_16x8_rom.v"
`include "./instruction_register.v"
`include "./accumulator.v"
`include "./b_register.v"
`include "./alu.v"
`include "./output_register.v"

module tt_um_jayraj4021_SAP1_cpu #( parameter MAX_COUNT = 10_000_000 ) (
    input  wire [7:0] ui_in,    // Dedicated inputs
    output wire [7:0] uo_out,   // Dedicated outputs
    input  wire [7:0] uio_in,   // IOs: Input path
    output wire [7:0] uio_out,  // IOs: Output path
    output wire [7:0] uio_oe,   // IOs: Enable path (active high: 0=input, 1=output)
    input  wire       ena,      // will go high when the design is enabled
    input  wire       clk,      // clock
    input  wire       rst_n     // reset_n - low to reset
);

    
    wire rst = ! rst_n;

    wire Epc, RstPc, Emar, LmPC, LmIRa, readEnableROM, Eir, Eacc, LaccM, LaccA, Eb, subtract, Eo;
    wire [3:0] pcAddressWire;
    wire [3:0] marAddressWire;
    wire [7:0] memoryDataWire;
    wire [7:0] irOutputWire;
    wire [7:0] accOutputWire;
    wire [7:0] bOutputWire;
    wire [7:0] aluOutputWire;
    //wire [7:0] orOutputWire;

    control_unit cu(.clk(clk), .rst(rst), .inputInstruction(irOutputWire), .Epc(Epc), .RstPc(RstPc), .Emar(Emar), .LmPC(LmPC), .LmIRa(LmIRa), .readEnableROM(readEnableROM), .Eir(Eir), .Eacc(Eacc), .LaccM(LaccM), .LaccA(LaccA), .Eb(Eb), .subtract(subtract), .Eo(Eo));
    program_counter pc(.clk(clk),.rst(RstPc),.Epc(Epc),.pc_address(pcAddressWire));
    mar mar(.clk(clk),.Emar(Emar),.LmPC(LmPC),.LmIRa(LmIRa),.addressFromPC(pcAddressWire),.addressFromIR(irOutputWire[3:0]),.outputAddress(marAddressWire));
    memory_16x8_rom memoryRom(.clk(clk), .readEnable(readEnableROM), .readAddress(marAddressWire), .dataOut(memoryDataWire));
    instruction_register ir(.clk(clk), .Eir(Eir), .inputInstruction(memoryDataWire), .outputInstruction(irOutputWire));
    accumulator acc(.clk(clk), .Eacc(Eacc), .LaccM(LaccM), .LaccA(LaccA), .inputDataFromMemory(memoryDataWire), .inputDataFromALU(aluOutputWire), .outputDataAcc(accOutputWire));
    b_register breg(.clk(clk), .Eb(Eb), .inputData(memoryDataWire), .outputData(bOutputWire));
    alu alu(.inputA(accOutputWire), .inputB(bOutputWire), .aluOutput(aluOutputWire), .subtract(subtract));
    output_register oreg(.clk(clk), .Eout(Eo), .inputData(accOutputWire), .outputData(uo_out));

endmodule

src/tt_um_jayraj4021_SAP1_cpu_tb.v
`timescale 1ns / 1ns
`include "tt_um_jayraj4021_SAP1_cpu.v"

module tt_um_jayraj4021_SAP1_cpu_tb;

    reg clk = 1'b0;
    reg rst_n = 1'b1;
    wire[7:0] uo_out ;
    wire[7:0] uio_out;
    wire[7:0] uio_oe;


    always begin
        clk = ~clk;
        #10;
    end

  /*  input  wire [7:0] ui_in,    // Dedicated inputs
    output wire [7:0] uo_out,   // Dedicated outputs
    input  wire [7:0] uio_in,   // IOs: Input path
    output wire [7:0] uio_out,  // IOs: Output path
    output wire [7:0] uio_oe,   // IOs: Enable path (active high: 0=input, 1=output)
    input  wire       ena,      // will go high when the design is enabled
    input  wire       clk,      // clock
    input  wire       rst_n     // reset_n - low to reset*/

    tt_um_jayraj4021_SAP1_cpu uut(.ui_in(),.uo_out(uo_out),.uio_in(),.uio_out(uio_out),.uio_oe(uio_oe),.clk(clk),.rst_n(rst_n));

    initial begin

        $dumpfile("tt_um_jayraj4021_SAP1_cpu_tb.vcd");
        $dumpvars(0,tt_um_jayraj4021_SAP1_cpu_tb);

        #25

        rst_n = 1'b0;
        #100

        rst_n = 1'b1;
        #2000

        $display("JD test done");
        $stop;
    end

endmodule

src/tt_um_jayraj4021_SAP1_cpu_tb.vcd
$date
	Sun Aug 27 19:30:31 2023
$end
$version
	Icarus Verilog
$end
$timescale
	1ns
$end
$scope module tt_um_jayraj4021_SAP1_cpu_tb $end
$var wire 8 ! uio_oe [7:0] $end
$var wire 8 " uio_out [7:0] $end
$var wire 8 # uo_out [7:0] $end
$var reg 1 $ clk $end
$var reg 1 % rst_n $end
$scope module uut $end
$var wire 1 & Eacc $end
$var wire 1 ' Eb $end
$var wire 1 ( Eir $end
$var wire 1 ) Emar $end
$var wire 1 * Eo $end
$var wire 1 + Epc $end
$var wire 1 , LaccA $end
$var wire 1 - LaccM $end
$var wire 1 . LmIRa $end
$var wire 1 / LmPC $end
$var wire 1 0 RstPc $end
$var wire 8 1 accOutputWire [7:0] $end
$var wire 8 2 aluOutputWire [7:0] $end
$var wire 8 3 bOutputWire [7:0] $end
$var wire 1 4 clk $end
$var wire 1 5 ena $end
$var wire 8 6 irOutputWire [7:0] $end
$var wire 4 7 marAddressWire [3:0] $end
$var wire 8 8 memoryDataWire [7:0] $end
$var wire 4 9 pcAddressWire [3:0] $end
$var wire 1 : readEnableROM $end
$var wire 1 ; rst $end
$var wire 1 < rst_n $end
$var wire 1 = subtract $end
$var wire 8 > ui_in [7:0] $end
$var wire 8 ? uio_in [7:0] $end
$var wire 8 @ uio_oe [7:0] $end
$var wire 8 A uio_out [7:0] $end
$var wire 8 B uo_out [7:0] $end
$scope module cu $end
$var wire 1 & Eacc $end
$var wire 1 ' Eb $end
$var wire 1 ( Eir $end
$var wire 1 ) Emar $end
$var wire 1 * Eo $end
$var wire 1 + Epc $end
$var wire 1 , LaccA $end
$var wire 1 - LaccM $end
$var wire 1 . LmIRa $end
$var wire 1 / LmPC $end
$var wire 1 0 RstPc $end
$var wire 1 4 clk $end
$var wire 8 C inputInstruction [7:0] $end
$var wire 1 : readEnableROM $end
$var wire 1 ; rst $end
$var wire 1 = subtract $end
$var reg 8 D next [7:0] $end
$var reg 8 E present [7:0] $end
$upscope $end
$scope module pc $end
$var wire 1 + Epc $end
$var wire 1 4 clk $end
$var wire 1 0 rst $end
$var reg 4 F pc_address [3:0] $end
$upscope $end
$scope module mar $end
$var wire 1 ) Emar $end
$var wire 1 . LmIRa $end
$var wire 1 / LmPC $end
$var wire 4 G addressFromIR [3:0] $end
$var wire 4 H addressFromPC [3:0] $end
$var wire 1 4 clk $end
$var reg 4 I outputAddress [3:0] $end
$upscope $end
$scope module memoryRom $end
$var wire 1 4 clk $end
$var wire 4 J readAddress [3:0] $end
$var wire 1 : readEnable $end
$var reg 8 K dataOut [7:0] $end
$upscope $end
$scope module ir $end
$var wire 1 ( Eir $end
$var wire 1 4 clk $end
$var wire 8 L inputInstruction [7:0] $end
$var reg 8 M outputInstruction [7:0] $end
$upscope $end
$scope module acc $end
$var wire 1 & Eacc $end
$var wire 1 , LaccA $end
$var wire 1 - LaccM $end
$var wire 1 4 clk $end
$var wire 8 N inputDataFromALU [7:0] $end
$var wire 8 O inputDataFromMemory [7:0] $end
$var reg 8 P outputDataAcc [7:0] $end
$upscope $end
$scope module breg $end
$var wire 1 ' Eb $end
$var wire 1 4 clk $end
$var wire 8 Q inputData [7:0] $end
$var reg 8 R outputData [7:0] $end
$upscope $end
$scope module alu $end
$var wire 8 S inputA [7:0] $end
$var wire 8 T inputB [7:0] $end
$var wire 1 = subtract $end
$var reg 8 U aluOutput [7:0] $end
$upscope $end
$scope module oreg $end
$var wire 1 * Eout $end
$var wire 1 4 clk $end
$var wire 8 V inputData [7:0] $end
$var reg 8 W outputData [7:0] $end
$upscope $end
$upscope $end
$upscope $end
$enddefinitions $end
#0
$dumpvars
bx W
bx V
bx U
bx T
bx S
bx R
bx Q
bx P
bx O
bx N
bx M
bx L
bx K
bx J
bx I
bx H
bx G
bx F
bx E
bx D
bx C
bx B
b11111111 A
b11111111 @
bz ?
bz >
x=
1<
0;
x:
bx 9
bx 8
bx 7
bx 6
z5
14
bx 3
bx 2
bx 1
x0
x/
x.
x-
x,
x+
x*
x)
x(
x'
x&
1%
1$
bx #
b11111111 "
b11111111 !
$end
#10
0$
04
#20
1$
14
#25
0%
0<
1;
#30
b0 F
b0 9
b0 H
0&
0=
0)
0:
0.
0-
0,
0'
b10 D
10
0/
0+
0(
0*
b1 E
0$
04
#40
1$
14
#50
0$
04
#60
1$
14
#70
0$
04
#80
1$
14
#90
0$
04
#100
1$
14
#110
0$
04
#120
1$
14
#125
1%
1<
0;
#130
1)
b100 D
00
1/
b10 E
0$
04
#140
b0 I
b0 7
b0 J
1$
14
#150
0)
1:
b1000 D
0/
1+
b100 E
0$
04
#160
b1001 K
b1001 8
b1001 L
b1001 O
b1001 Q
b1 F
b1 9
b1 H
1$
14
#170
0:
b10000 D
0+
1(
b1000 E
0$
04
#180
b10000 D
b1001 G
b1001 M
b1001 6
b1001 C
1$
14
#190
1)
1.
b100000 D
0(
b10000 E
0$
04
#200
b1001 I
b1001 7
b1001 J
1$
14
#210
0)
1:
0.
b1000000 D
b100000 E
0$
04
#220
b1 K
b1 8
b1 L
b1 O
b1 Q
1$
14
#230
0:
1&
1-
b10000000 D
b1000000 E
0$
04
#240
b1 P
b1 1
b1 S
b1 V
1$
14
#250
0&
0-
b10 D
b10000000 E
0$
04
#260
1$
14
#270
1)
b100 D
1/
b10 E
0$
04
#280
b1 I
b1 7
b1 J
1$
14
#290
0)
1:
b1000 D
0/
1+
b100 E
0$
04
#300
b11101111 K
b11101111 8
b11101111 L
b11101111 O
b11101111 Q
b10 F
b10 9
b10 H
1$
14
#310
0:
b10000 D
0+
1(
b1000 E
0$
04
#320
b10000 D
b1111 G
b11101111 M
b11101111 6
b11101111 C
1$
14
#330
b100000 D
0(
1*
b10000 E
0$
04
#340
b1 W
b1 #
b1 B
1$
14
#350
b1000000 D
0*
b100000 E
0$
04
#360
1$
14
#370
b10000000 D
b1000000 E
0$
04
#380
1$
14
#390
b10 D
b10000000 E
0$
04
#400
1$
14
#410
1)
b100 D
1/
b10 E
0$
04
#420
b10 I
b10 7
b10 J
1$
14
#430
0)
1:
b1000 D
0/
1+
b100 E
0$
04
#440
b11010 K
b11010 8
b11010 L
b11010 O
b11010 Q
b11 F
b11 9
b11 H
1$
14
#450
0:
b10000 D
0+
1(
b1000 E
0$
04
#460
b10000 D
b1010 G
b11010 M
b11010 6
b11010 C
1$
14
#470
1)
1.
b100000 D
0(
b10000 E
0$
04
#480
b1010 I
b1010 7
b1010 J
1$
14
#490
0)
1:
0.
b1000000 D
b100000 E
0$
04
#500
b10 K
b10 8
b10 L
b10 O
b10 Q
1$
14
#510
0:
1'
b10000000 D
b1000000 E
0$
04
#520
b11 U
b11 2
b11 N
b10 R
b10 3
b10 T
1$
14
#530
1&
1,
0'
b10 D
b10000000 E
0$
04
#540
b101 U
b101 2
b101 N
b11 P
b11 1
b11 S
b11 V
1$
14
#550
0&
1)
0,
b100 D
1/
b10 E
0$
04
#560
b11 I
b11 7
b11 J
1$
14
#570
0)
1:
b1000 D
0/
1+
b100 E
0$
04
#580
b11101111 K
b11101111 8
b11101111 L
b11101111 O
b11101111 Q
b100 F
b100 9
b100 H
1$
14
#590
0:
b10000 D
0+
1(
b1000 E
0$
04
#600
b10000 D
b1111 G
b11101111 M
b11101111 6
b11101111 C
1$
14
#610
b100000 D
0(
1*
b10000 E
0$
04
#620
b11 W
b11 #
b11 B
1$
14
#630
b1000000 D
0*
b100000 E
0$
04
#640
1$
14
#650
b10000000 D
b1000000 E
0$
04
#660
1$
14
#670
b10 D
b10000000 E
0$
04
#680
1$
14
#690
1)
b100 D
1/
b10 E
0$
04
#700
b100 I
b100 7
b100 J
1$
14
#710
0)
1:
b1000 D
0/
1+
b100 E
0$
04
#720
b11011 K
b11011 8
b11011 L
b11011 O
b11011 Q
b101 F
b101 9
b101 H
1$
14
#730
0:
b10000 D
0+
1(
b1000 E
0$
04
#740
b10000 D
b1011 G
b11011 M
b11011 6
b11011 C
1$
14
#750
1)
1.
b100000 D
0(
b10000 E
0$
04
#760
b1011 I
b1011 7
b1011 J
1$
14
#770
0)
1:
0.
b1000000 D
b100000 E
0$
04
#780
b11 K
b11 8
b11 L
b11 O
b11 Q
1$
14
#790
0:
1'
b10000000 D
b1000000 E
0$
04
#800
b110 U
b110 2
b110 N
b11 R
b11 3
b11 T
1$
14
#810
1&
1,
0'
b10 D
b10000000 E
0$
04
#820
b1001 U
b1001 2
b1001 N
b110 P
b110 1
b110 S
b110 V
1$
14
#830
0&
1)
0,
b100 D
1/
b10 E
0$
04
#840
b101 I
b101 7
b101 J
1$
14
#850
0)
1:
b1000 D
0/
1+
b100 E
0$
04
#860
b11101111 K
b11101111 8
b11101111 L
b11101111 O
b11101111 Q
b110 F
b110 9
b110 H
1$
14
#870
0:
b10000 D
0+
1(
b1000 E
0$
04
#880
b10000 D
b1111 G
b11101111 M
b11101111 6
b11101111 C
1$
14
#890
b100000 D
0(
1*
b10000 E
0$
04
#900
b110 W
b110 #
b110 B
1$
14
#910
b1000000 D
0*
b100000 E
0$
04
#920
1$
14
#930
b10000000 D
b1000000 E
0$
04
#940
1$
14
#950
b10 D
b10000000 E
0$
04
#960
1$
14
#970
1)
b100 D
1/
b10 E
0$
04
#980
b110 I
b110 7
b110 J
1$
14
#990
0)
1:
b1000 D
0/
1+
b100 E
0$
04
#1000
b101100 K
b101100 8
b101100 L
b101100 O
b101100 Q
b111 F
b111 9
b111 H
1$
14
#1010
0:
b10000 D
0+
1(
b1000 E
0$
04
#1020
b10000 D
b1100 G
b101100 M
b101100 6
b101100 C
1$
14
#1030
1)
1.
b100000 D
0(
b10000 E
0$
04
#1040
b1100 I
b1100 7
b1100 J
1$
14
#1050
0)
1:
0.
b1000000 D
b100000 E
0$
04
#1060
b100 K
b100 8
b100 L
b100 O
b100 Q
1$
14
#1070
b11 U
b11 2
b11 N
0:
1=
1'
b10000000 D
b1000000 E
0$
04
#1080
b10 U
b10 2
b10 N
b100 R
b100 3
b100 T
1$
14
#1090
1&
1,
0'
b10 D
b10000000 E
0$
04
#1100
b11111110 U
b11111110 2
b11111110 N
b10 P
b10 1
b10 S
b10 V
1$
14
#1110
b110 U
b110 2
b110 N
0&
0=
1)
0,
b100 D
1/
b10 E
0$
04
#1120
b111 I
b111 7
b111 J
1$
14
#1130
0)
1:
b1000 D
0/
1+
b100 E
0$
04
#1140
b11101111 K
b11101111 8
b11101111 L
b11101111 O
b11101111 Q
b1000 F
b1000 9
b1000 H
1$
14
#1150
0:
b10000 D
0+
1(
b1000 E
0$
04
#1160
b10000 D
b1111 G
b11101111 M
b11101111 6
b11101111 C
1$
14
#1170
b100000 D
0(
1*
b10000 E
0$
04
#1180
b10 W
b10 #
b10 B
1$
14
#1190
b1000000 D
0*
b100000 E
0$
04
#1200
1$
14
#1210
b10000000 D
b1000000 E
0$
04
#1220
1$
14
#1230
b10 D
b10000000 E
0$
04
#1240
1$
14
#1250
1)
b100 D
1/
b10 E
0$
04
#1260
b1000 I
b1000 7
b1000 J
1$
14
#1270
0)
1:
b1000 D
0/
1+
b100 E
0$
04
#1280
b1001 F
b1001 9
b1001 H
1$
14
#1290
0:
b10000 D
0+
1(
b1000 E
0$
04
#1300
1$
14
#1310
b100000 D
0(
1*
b10000 E
0$
04
#1320
1$
14
#1330
b1000000 D
0*
b100000 E
0$
04
#1340
1$
14
#1350
b10000000 D
b1000000 E
0$
04
#1360
1$
14
#1370
b10 D
b10000000 E
0$
04
#1380
1$
14
#1390
1)
b100 D
1/
b10 E
0$
04
#1400
b1001 I
b1001 7
b1001 J
1$
14
#1410
0)
1:
b1000 D
0/
1+
b100 E
0$
04
#1420
b1 K
b1 8
b1 L
b1 O
b1 Q
b1010 F
b1010 9
b1010 H
1$
14
#1430
0:
b10000 D
0+
1(
b1000 E
0$
04
#1440
b10000 D
b1 G
b1 M
b1 6
b1 C
1$
14
#1450
1)
1.
b100000 D
0(
b10000 E
0$
04
#1460
b1 I
b1 7
b1 J
1$
14
#1470
0)
1:
0.
b1000000 D
b100000 E
0$
04
#1480
b11101111 K
b11101111 8
b11101111 L
b11101111 O
b11101111 Q
1$
14
#1490
0:
1&
1-
b10000000 D
b1000000 E
0$
04
#1500
b11110011 U
b11110011 2
b11110011 N
b11101111 P
b11101111 1
b11101111 S
b11101111 V
1$
14
#1510
0&
0-
b10 D
b10000000 E
0$
04
#1520
1$
14
#1530
1)
b100 D
1/
b10 E
0$
04
#1540
b1010 I
b1010 7
b1010 J
1$
14
#1550
0)
1:
b1000 D
0/
1+
b100 E
0$
04
#1560
b10 K
b10 8
b10 L
b10 O
b10 Q
b1011 F
b1011 9
b1011 H
1$
14
#1570
0:
b10000 D
0+
1(
b1000 E
0$
04
#1580
b10000 D
b10 G
b10 M
b10 6
b10 C
1$
14
#1590
1)
1.
b100000 D
0(
b10000 E
0$
04
#1600
b10 I
b10 7
b10 J
1$
14
#1610
0)
1:
0.
b1000000 D
b100000 E
0$
04
#1620
b11010 K
b11010 8
b11010 L
b11010 O
b11010 Q
1$
14
#1630
0:
1&
1-
b10000000 D
b1000000 E
0$
04
#1640
b11110 U
b11110 2
b11110 N
b11010 P
b11010 1
b11010 S
b11010 V
1$
14
#1650
0&
0-
b10 D
b10000000 E
0$
04
#1660
1$
14
#1670
1)
b100 D
1/
b10 E
0$
04
#1680
b1011 I
b1011 7
b1011 J
1$
14
#1690
0)
1:
b1000 D
0/
1+
b100 E
0$
04
#1700
b11 K
b11 8
b11 L
b11 O
b11 Q
b1100 F
b1100 9
b1100 H
1$
14
#1710
0:
b10000 D
0+
1(
b1000 E
0$
04
#1720
b10000 D
b11 G
b11 M
b11 6
b11 C
1$
14
#1730
1)
1.
b100000 D
0(
b10000 E
0$
04
#1740
b11 I
b11 7
b11 J
1$
14
#1750
0)
1:
0.
b1000000 D
b100000 E
0$
04
#1760
b11101111 K
b11101111 8
b11101111 L
b11101111 O
b11101111 Q
1$
14
#1770
0:
1&
1-
b10000000 D
b1000000 E
0$
04
#1780
b11110011 U
b11110011 2
b11110011 N
b11101111 P
b11101111 1
b11101111 S
b11101111 V
1$
14
#1790
0&
0-
b10 D
b10000000 E
0$
04
#1800
1$
14
#1810
1)
b100 D
1/
b10 E
0$
04
#1820
b1100 I
b1100 7
b1100 J
1$
14
#1830
0)
1:
b1000 D
0/
1+
b100 E
0$
04
#1840
b100 K
b100 8
b100 L
b100 O
b100 Q
b1101 F
b1101 9
b1101 H
1$
14
#1850
0:
b10000 D
0+
1(
b1000 E
0$
04
#1860
b10000 D
b100 G
b100 M
b100 6
b100 C
1$
14
#1870
1)
1.
b100000 D
0(
b10000 E
0$
04
#1880
b100 I
b100 7
b100 J
1$
14
#1890
0)
1:
0.
b1000000 D
b100000 E
0$
04
#1900
b11011 K
b11011 8
b11011 L
b11011 O
b11011 Q
1$
14
#1910
0:
1&
1-
b10000000 D
b1000000 E
0$
04
#1920
b11111 U
b11111 2
b11111 N
b11011 P
b11011 1
b11011 S
b11011 V
1$
14
#1930
0&
0-
b10 D
b10000000 E
0$
04
#1940
1$
14
#1950
1)
b100 D
1/
b10 E
0$
04
#1960
b1101 I
b1101 7
b1101 J
1$
14
#1970
0)
1:
b1000 D
0/
1+
b100 E
0$
04
#1980
b11111111 K
b11111111 8
b11111111 L
b11111111 O
b11111111 Q
b1110 F
b1110 9
b1110 H
1$
14
#1990
0:
b10000 D
0+
1(
b1000 E
0$
04
#2000
b10000 D
b1111 G
b11111111 M
b11111111 6
b11111111 C
1$
14
#2010
b100000 D
0(
b10000 E
0$
04
#2020
1$
14
#2030
b1000000 D
b100000 E
0$
04
#2040
1$
14
#2050
b10000000 D
b1000000 E
0$
04
#2060
1$
14
#2070
b10 D
b10000000 E
0$
04
#2080
1$
14
#2090
1)
b100 D
1/
b10 E
0$
04
#2100
b1110 I
b1110 7
b1110 J
1$
14
#2110
0)
1:
b1000 D
0/
1+
b100 E
0$
04
#2120
b1111 F
b1111 9
b1111 H
1$
14
